main.py
burgerpizza-1.0.dist-info/METADATA
burgerpizza-1.0.dist-info/WHEEL
burgerpizza-1.0.dist-info/top_level.txt
burgerpizza-1.0.dist-info/RECORD
