Metadata-Version: 2.1
Name: burgerpizza
Version: 1.0
Summary: this is a file that icreated
Home-page: UNKNOWN
Author: Ibrahim biryani zaheer
Author-email: zaheeribrahim346@gmail.com
License: license.txt
Platform: UNKNOWN
